<?xml version='1.0' encoding='UTF-8'?>
<tv date="20250911205623 +0800" generator-info-name="epg.pw" generator-info-url="https://epg.pw/channels/369264/20250911.html" source-info-name="FREE EPG" source-info-url="https://epg.pw/api/epg.xml?channel_id=369264&amp;date=20250911&amp;timezone=QXNpYS9UYWlwZWk=">
  <channel id="369264">
    <display-name lang="Taiwan">HBO</display-name>
    <icon src="https://epg.pw/media/images/epg/2024/06/11/20240611151927515270_35.png" />
  </channel>
  <programme channel="369264" start="20250911014000 +0800" stop="20250911033500 +0800">
    <title lang="zh">火線掏寶</title>
    <desc>本片描寫兩個年輕小夥子竟成為美國政府的主要軍火供應商，最後拿下的3億美元合約卻讓他們愈陷愈深…</desc>
    <date>2025-09-11</date>
  </programme>
  <programme channel="369264" start="20250911033500 +0800" stop="20250911052000 +0800">
    <title lang="zh">狼人</title>
    <desc>滿月高懸，恐懼逼真來襲。一名男子為了保護家人、決心對抗致命掠食者</desc>
    <date>2025-09-11</date>
  </programme>
  <programme channel="369264" start="20250911052000 +0800" stop="20250911054500 +0800">
    <title lang="zh">好萊塢好好看第1季:1133</title>
    <desc>本節目每週深入幕後與片場，介紹三部強檔電影的製作過程，內含動作片段與演員及製作人的採訪</desc>
    <date>2025-09-11</date>
  </programme>
  <programme channel="369264" start="20250911054500 +0800" stop="20250911070500 +0800">
    <title lang="zh">聖誕劫前夕</title>
    <desc>這部溫馨的佳節電視電影以10歲的米奇為主角，他在北愛爾蘭農村長大，出身卑微讓他對聖誕老人和聖誕節感到憤世嫉俗。有一天，他和弟弟尚恩在樹林裡發現從雪橇上掉下來的聖誕老人，但隨後又有另一位聖誕老人出現，手裡拿著一袋偷來的錢。哪一個聖誕老人才能幫助米奇重新發現聖誕節的真正意義呢？</desc>
    <date>2025-09-11</date>
  </programme>
  <programme channel="369264" start="20250911070500 +0800" stop="20250911090500 +0800">
    <title lang="zh">伴娘我最大</title>
    <desc>女孩受邀擔任好姊妹的伴娘，但在伴娘團中卻殺出超極強敵－嚴重威脅她在姊妹心中的地位。</desc>
    <date>2025-09-11</date>
  </programme>
  <programme channel="369264" start="20250911090500 +0800" stop="20250911104000 +0800">
    <title lang="zh">狗狗史酷比！</title>
    <desc>史酷比冒險行動首次躍上大螢幕，述說史酷比的來源以及神秘偵探社迄今所遇到的最難解的謎團</desc>
    <date>2025-09-11</date>
  </programme>
  <programme channel="369264" start="20250911104000 +0800" stop="20250911120500 +0800">
    <title lang="zh">歲月輪迴</title>
    <desc>瑞秋在循環的時間中受困，不斷重複經歷父母的光明節派對之夜。奶奶想撮合的「好男孩」札克，能幫助她渡過難關，迎接明天嗎？</desc>
    <date>2025-09-11</date>
  </programme>
  <programme channel="369264" start="20250911120500 +0800" stop="20250911134500 +0800">
    <title lang="zh">尋找新樂園</title>
    <desc>本片是J.M巴利的半自傳電影，內容描述他如何得到啟發，寫下經典童書彼得潘</desc>
    <date>2025-09-11</date>
  </programme>
  <programme channel="369264" start="20250911134500 +0800" stop="20250911153000 +0800">
    <title lang="zh">恐怖社區</title>
    <desc>本片由新生代紅星西亞李畢福（變型金剛）主演。描述父親過世,忙於賺錢的母親無暇照顧的問題青年凱爾,以偷窺鄰居生活為樂。但他竟發現鄰居是一名連續殺人魔</desc>
    <date>2025-09-11</date>
  </programme>
  <programme channel="369264" start="20250911153000 +0800" stop="20250911170000 +0800">
    <title lang="zh">寵物當家</title>
    <desc>主人離家後，寵物究竟在做什麼？同棟樓的寵物會和朋友聊八卦、吃甜食、辦派對，但有天牠們迷失在紐約的都市叢林裡，必須要放下歧見，努力找到回家的路</desc>
    <date>2025-09-11</date>
  </programme>
  <programme channel="369264" start="20250911170000 +0800" stop="20250911191000 +0800">
    <title lang="zh">滯留生</title>
    <desc>一名叛逆的學生、一位惡名昭彰且惹人嫌的教授和學校主廚在聖誕假期期間成為了意想不到的夥伴，因為只有他們留在校園。他們互相幫助，讓彼此明白他們不受過去束縛</desc>
    <date>2025-09-11</date>
  </programme>
  <programme channel="369264" start="20250911191000 +0800" stop="20250911210000 +0800">
    <title lang="zh">潘恩-航向夢幻島</title>
    <desc>孤兒彼得被帶往神奇的夢幻島，在這裡他找到樂趣也遭受危險，最後發現自己真正的命運-成為世人所熟知的英雄彼得潘</desc>
    <date>2025-09-11</date>
  </programme>
  <programme channel="369264" start="20250911210000 +0800" stop="20250911223500 +0800">
    <title lang="zh">陰間大法師</title>
    <desc>因車禍兩夫妻變成鬼被困在原本的家，一對來自紐約的暴發戶帶著死氣沈沈的女兒搬進他們的家後，令這對鬼夫妻覺得備受威脅，因而決定”扮”鬼趕走這幾位不請自來的新住戶，但卻始終毫無成效…</desc>
    <date>2025-09-11</date>
  </programme>
  <programme channel="369264" start="20250911223500 +0800" stop="20250912000000 +0800">
    <title lang="zh">火線掏寶</title>
    <desc>本片描寫兩個年輕小夥子竟成為美國政府的主要軍火供應商，最後拿下的3億美元合約卻讓他們愈陷愈深…</desc>
    <date>2025-09-11</date>
  </programme>
  <programme channel="369264" start="20250912002500 +0800" stop="20250912021000 +0800">
    <title lang="zh">天使營救</title>
    <desc>2021年美國從阿富汗撤軍後，一群女兵被派回阿富汗去營救一群被綁架的青少年</desc>
    <date>2025-09-12</date>
  </programme>
  <programme channel="369264" start="20250912021000 +0800" stop="20250912034500 +0800">
    <title lang="zh">隱秘的自我</title>
    <desc>安娜愛上了尼克，但她的雙胞胎妹妹柔伊察覺其中有詐。她們陷入了一場危險的遊戲，在這場遊戲中，誠實可能招來致命的後果。</desc>
    <date>2025-09-12</date>
  </programme>
  <programme channel="369264" start="20250912034500 +0800" stop="20250913000000 +0800">
    <title lang="zh">哭泣的女人</title>
    <desc>本片描寫一名社工師無視某個察覺到孩子危險的焦慮母親的怪異警告，進而與她年幼的孩子們被拉進駭人的超自然空間裡…</desc>
    <date>2025-09-12</date>
  </programme>
</tv>
