<?xml version='1.0' encoding='UTF-8'?>
<tv date="20250306072613 +0800" generator-info-name="epg.pw" generator-info-url="https://epg.pw/channels/369262/20250306.html" source-info-name="FREE EPG" source-info-url="https://epg.pw/api/epg.xml?channel_id=369262&amp;date=20250306&amp;timezone=QXNpYS9UYWlwZWk=">
  <channel id="369262">
    <display-name lang="Taiwan">緯來電影台</display-name>
    <icon src="https://epg.pw/media/images/epg/2024/06/11/20240611151856162713_69.png" />
  </channel>
  <programme channel="369262" start="20250306010500 +0800" stop="20250306040000 +0800">
    <title lang="zh">跛豪</title>
    <desc>呂良偉飾演六○年代香港黑道傳奇人物──跛豪，他過去因曾遭到伏擊受傷變成跛子，號「跛豪」。心有不甘的跛豪，設計陷害對頭肥波（鄭則仕飾），安排他藏有毒品入獄，再緊抓住探長的弱點，用黑錢賄賂他，使出一連串的計謀，剷除異己，整飭黑道，但終因得罪的人太多，事跡敗露，為人黑吃黑，即使探長想幫他，也礙莫能助……。</desc>
    <date>2025-03-06</date>
  </programme>
  <programme channel="369262" start="20250306040000 +0800" stop="20250306050000 +0800">
    <title lang="zh">神醫喜來樂傳奇:4</title>
    <desc>清末，滄州民間神醫喜來樂因得罪朝廷權貴，被流放東北。時至庚子年，八國聯軍入侵北京，喜來樂又被捲入時代的漩渦中。侵略者水土不服身染怪病，西醫束手無策，喜來樂的死對頭向洋鬼子舉薦喜來樂當軍醫。 但喜來樂不願當漢奸，出逃以致身陷匪巢，卻意外受到匪首之女金山嬌的青睞。</desc>
    <date>2025-03-06</date>
  </programme>
  <programme channel="369262" start="20250306050000 +0800" stop="20250306072000 +0800">
    <title lang="zh">七小福</title>
    <desc>頑童阿龍出身貧窮，母親把他送進了于占元辦的戲劇學院。從此，他和小師兄弟三毛、阿彪等一起練功，念戲白、畫臉譜，生活十分艱苦清貧。師傅于占元忠直淳厚，他在困難條件下苦心經營，一方面對徒弟無比嚴厲，一方面對他們備加呵護，希望他們能繼承戲劇的良好傳統。大弟子三毛身手不凡，是同輩中的領袖。隨著年齡增長，這些孩子們的技藝與日俱增，他們一起到梨園獻藝，參加各種演出。</desc>
    <date>2025-03-06</date>
  </programme>
  <programme channel="369262" start="20250306072000 +0800" stop="20250306093500 +0800">
    <title lang="zh">給爸爸的信</title>
    <desc>鞏偉（李連杰飾）乃中國公安特警，被派混入香港犯罪集團， 調查涉及國內貪污等嚴重罪行。為取得甫光（於榮光飾）信任， 鞏偉參加一個黑吃黑行動，與悍匪在鬧市火拼，大隊警員趕到。 鞏偉只好挾持方逸華督察（梅豔芳飾）跟警方對恃，逃走過程中，遇上襲擊。 鞏偉奮力保護方逸華，令她深感這不見容貌的蒙面匪徒並非一般冷血之輩。</desc>
    <date>2025-03-06</date>
  </programme>
  <programme channel="369262" start="20250306093500 +0800" stop="20250306114500 +0800">
    <title lang="zh">快餐車</title>
    <desc>成龍和元彪移民到歐洲，經營了一個快餐車維生，有一天在廣場販賣時，碰到一個美女被人追殺，成龍和元彪於是見義勇為，救了這個美女……不料，這位美女和黑道結仇，他們兩個於是被捲入整個事件當中……他們要如何解救？</desc>
    <date>2025-03-06</date>
  </programme>
  <programme channel="369262" start="20250306114500 +0800" stop="20250306141000 +0800">
    <title lang="zh">賭俠1999</title>
    <desc>King（劉德華 飾）頭腦靈活，機智過人，憑著其銳利的眼光、十足的把握在賭場叱吒一時無人能及，被譽為賭神接班人。 在一次赴會，其弟Jack不幸被兇悍的殺手煙通（吳毅將 飾）所殺，KING重傷之餘亦意外錯殺煙通，被警方判以誤殺罪名監禁五年。大著肚子的妻子與拍檔虫（張錦程飾）捨他而去。在KING出獄後追尋許久也不曾發現兩人下落。 化骨龍（張家輝 飾）終日無所事事，人生哲學是「人生如賭博、有賭未為輸」，視King為偶像，希望能學一招半式的賭博技倆，二人亦成為知交，交心的好拍檔。晴（朱茵 飾），化骨龍的親妹，爽朗、可愛、善解人意，愛情上波折重重常被俊男所騙，自King與龍踢爆其男友職業是鴨，並安排難忘的盛大生日會，晴開始對King大生好感。</desc>
    <date>2025-03-06</date>
  </programme>
  <programme channel="369262" start="20250306141000 +0800" stop="20250306160500 +0800">
    <title lang="zh">逃學英雄傳</title>
    <desc>警方談判專家侯瑞堅（張堅庭飾）膽小又糊塗，常常出錯，幸得外號「奪命剪刀腳」的舅父保住飯碗，一次勸降行動中，堅誤打誤撞捉到了悍匪喪波，波誓言報仇。 堅被派往聖育強中學做臥底教師，尋找台灣黑幫份子兒子小狗的下落。沒想到，學校裡全是問題學生，其中就以化名A士（郭富城飾），其實就是小狗的學生最調皮。同時，學校中還有警方線人、黑幫臥底、美麗女教師林夢想（張敏飾）和有案底的教師蟹哥（陳惠敏飾），加上堅的警花女友卿（邱淑貞飾）也冒成學生來校園查案，將學校弄得一團混亂...。 就在一切毫無頭緒時，「鐵布衫」黑幫老大也從台灣來到香港，誓言要殺掉小狗...。</desc>
    <date>2025-03-06</date>
  </programme>
  <programme channel="369262" start="20250306160500 +0800" stop="20250306180000 +0800">
    <title lang="zh">開心鬼</title>
    <desc>朱秀才連考十多次也未中狀元，老父因此氣得病逝，老婆也離他而去，無奈之下朱在一座廟裡懸樑自盡，不料心中有冤屈，無法投胎轉世，靈魂只有附在自盡那條麻繩上。 八十年代，高中學生林青青、林小花及顏如玉在假期旅行中為避暴風雨，誤闖進古廟，青在忙亂中將麻繩帶回宿舍，靈魂附在麻繩上的朱也跟被帶進學校，鬧出不少笑話。朱與她們成了好朋友，並規勸她們要靠自己的能力去創造未來，而朱亦因此沉冤得雪，投胎轉世。</desc>
    <date>2025-03-06</date>
  </programme>
  <programme channel="369262" start="20250306180000 +0800" stop="20250306190000 +0800">
    <title lang="zh">少年包青天3:6</title>
    <desc>兩年前，包拯接到一封信，便匆匆離開家園，之後音訊全無。這些年裡，每當有奇案發生，公孫策便會趕赴現場，目的其實是為了尋找包拯。因公孫策諳遼語，仁宗遂委公孫策為禮部侍郎，前往宋遼邊境洽談議和。在邊境小鎮，公孫策和展昭遇到了大包——失去記憶成為妓院小雜工的包拯。失憶後的包拯傻裡傻氣，常被妓院裡的小丫鬟小蠻欺負。妓院老闆及遼國大官相繼神秘被殺，包拯找到了真凶，真凶欲殺包拯滅口，但他卻因禍得福恢復了記憶。</desc>
    <date>2025-03-06</date>
  </programme>
  <programme channel="369262" start="20250306190000 +0800" stop="20250306200000 +0800">
    <title lang="zh">倚天屠龍記:27</title>
    <desc>由楚原改編及執導，由羅烈飾金毛獅王謝遜、爾冬陞飾張無忌。劇情描述武林中人都在爭奪倚天劍、屠龍刀這兩件神器；只要這兩件神器一併，就可雄霸武林…</desc>
    <date>2025-03-06</date>
  </programme>
  <programme channel="369262" start="20250306200000 +0800" stop="20250306203000 +0800">
    <title lang="zh">實習醫師鬥格:235</title>
    <desc>改編自骨科陳建仁醫師作品的歡笑喜劇，從實習醫師的觀點來演繹白色巨塔的故事，是一部笑中帶尷尬的喜劇。</desc>
    <date>2025-03-06</date>
  </programme>
  <programme channel="369262" start="20250306203000 +0800" stop="20250306210000 +0800">
    <title lang="zh">實習醫師鬥格:236</title>
    <desc>改編自骨科陳建仁醫師作品的歡笑喜劇，從實習醫師的觀點來演繹白色巨塔的故事，是一部笑中帶尷尬的喜劇。</desc>
    <date>2025-03-06</date>
  </programme>
  <programme channel="369262" start="20250306210000 +0800" stop="20250306232000 +0800">
    <title lang="zh">奇謀妙計五福星</title>
    <desc>茶壺、死氣喉、凡士林、鬈毛積及劉克司五人出獄後決定改邪歸正，與鬈毛積的妹妹（妹頭）同組「五寶清潔公司」。某次匪徒正交易偽鈔電版時遇上劫匪，剛巧被 CID 看見便一路追趕，後劫匪情急下將電版拋進五福星之清潔車中。五寶開始被兩大反派追殺，最後五福星施展奇謀妙計應付兩大反派。</desc>
    <date>2025-03-06</date>
  </programme>
  <programme channel="369262" start="20250306232000 +0800" stop="20250307000000 +0800">
    <title lang="zh">羔羊遊戲</title>
    <desc>雪麗在婚禮現場遭劫匪挾持，目睹丈夫死於匪徒槍下。無法走出陰霾的她現於一家射箭館任職。颱風之夜，她意外滯留樓內，目擊同一幫匪徒在大廈內殺人，她不慎暴露了自己的蹤跡，逃亡中她遇到了盲眼老人南哥，兩人邊抵抗匪徒追殺，邊設法逃離。窮凶極惡的匪徒欲殺人滅口，兩人苦苦找尋著活下去的辦法……</desc>
    <date>2025-03-06</date>
  </programme>
  <programme channel="369262" start="20250307011500 +0800" stop="20250307035000 +0800">
    <title lang="zh">阿呆</title>
    <desc>劇情描述農村出身的阿呆，為了擺脫不幸的家庭而到臺北打拚，成為林董的貼身保鏢。警方掃黑時，林董帶著情婦出國避風頭，阿呆跟獨守空房的林太太漸生情愫，但後來他仍被林太太出賣了。蔡岳勳飾演阿呆和餘天飾演林董都表現不錯，但叢珊內斂的蛇蝎美人形象最成功。</desc>
    <date>2025-03-07</date>
  </programme>
  <programme channel="369262" start="20250307035000 +0800" stop="20250307045000 +0800">
    <title lang="zh">神醫喜來樂傳奇:5</title>
    <desc>清末，滄州民間神醫喜來樂因得罪朝廷權貴，被流放東北。時至庚子年，八國聯軍入侵北京，喜來樂又被捲入時代的漩渦中。侵略者水土不服身染怪病，西醫束手無策，喜來樂的死對頭向洋鬼子舉薦喜來樂當軍醫。 但喜來樂不願當漢奸，出逃以致身陷匪巢，卻意外受到匪首之女金山嬌的青睞。</desc>
    <date>2025-03-07</date>
  </programme>
  <programme channel="369262" start="20250307045000 +0800" stop="20250307071500 +0800">
    <title lang="zh">成功補習班</title>
    <desc>在1994年升學至上、嚴禁戀愛的年代，青春正盛、賀爾蒙噴發的三人是成功補習班的麻煩人物，三個人的友誼，因為補習班班花林奕嵐，開始有了奇妙的關係變化，此時補習班出現了一位不按牌理出牌的新任老師侯彥西，帶著三劍客展開一段尋找自我的旅程。</desc>
    <date>2025-03-07</date>
  </programme>
  <programme channel="369262" start="20250307071500 +0800" stop="20250307091500 +0800">
    <title lang="zh">熱血格鬥</title>
    <desc>轉學到新學校的卡爾，加入了武術社，並迷戀上崇拜者無數的美麗功夫女孩卡翠。當他依照內心的渴望行動時，麻煩似乎也接踵而來。與此同時，一名傳統武術大師的傳人兼兒子，在父親與MMA冠軍對戰身亡後，為了復仇與復興傳統武術的聲譽而努力。</desc>
    <date>2025-03-07</date>
  </programme>
  <programme channel="369262" start="20250307091500 +0800" stop="20250307112000 +0800">
    <title lang="zh">古惑仔3之隻手遮天</title>
    <desc>香港在繁榮的背後，同時也是罪惡的溫床。蔣天生領導的洪興社是較活躍的社團，駱駝的東英社也蠢蠢欲動，其中「東英雙虎」烏鴉和笑面虎更是兇殘暴暴戾。笑面虎用計在陳酒吧對面開卡拉OK，並請洪興社的基當看場，正式威脅陳，而烏鴉的挑釁引起蔣的不滿，蔣天生與駱駝談判，駱警告烏，烏不忿。蔣天生同女伴（一影視女星）、陳歐遊、烏鴉和笑面虎派殺手伏擊蔣天生劫擄女星，並嫁禍陳。</desc>
    <date>2025-03-07</date>
  </programme>
  <programme channel="369262" start="20250307112000 +0800" stop="20250307134000 +0800">
    <title lang="zh">奇謀妙計五福星</title>
    <desc>茶壺、死氣喉、凡士林、鬈毛積及劉克司五人出獄後決定改邪歸正，與鬈毛積的妹妹（妹頭）同組「五寶清潔公司」。某次匪徒正交易偽鈔電版時遇上劫匪，剛巧被 CID 看見便一路追趕，後劫匪情急下將電版拋進五福星之清潔車中。五寶開始被兩大反派追殺，最後五福星施展奇謀妙計應付兩大反派。</desc>
    <date>2025-03-07</date>
  </programme>
  <programme channel="369262" start="20250307134000 +0800" stop="20250307160000 +0800">
    <title lang="zh">我們全家不太熟</title>
    <desc>即將畢業的威力苦惱著是否要繼承父親衣缽；室友大胖遲遲不敢跟暗戀的女生告白；另一個室友啞牙則是沒自信的怪咖。迷惘的三人某天回到家，發現一個裝滿錢的信封，便拿去花光了。此時，赴澳洲打工的好友卡卡帶了一個嬰兒回家，原來那些錢是準備付給保母的，無力償還的三人只好硬著頭皮接下了保母工作…</desc>
    <date>2025-03-07</date>
  </programme>
  <programme channel="369262" start="20250307160000 +0800" stop="20250307180000 +0800">
    <title lang="zh">百變金剛</title>
    <desc>阿星在夏威夷某大學讀書，常仗著自己是校董的兒子，欺凌他人。沒人敢反抗，唯獨人體學博士，及其女兒蟲蟲，敢戲弄他。 阿星和蟲蟲是同學，兩人互看不順眼，阿星看不慣蟲蟲四眼田雞、暴牙妹的模樣，蟲蟲則看不慣阿星敗家公子樣。 某日，星得知自己非校董的兒子，知道管家達叔才是他的父親，然而，星卻見錢忘義，把達趕出。 雖然如此，星的內心很矛盾...他到教堂懺悔，遇蟲蟲，蟲蟲見他後悔難過的樣子，便對他另眼看待。 星和一美豔女子Silvia去舞廳，但是，他們遇到Silvia的老公Roberto。R是黑社會老大，見他倆親熱，乃下令追殺阿星。達協助星對抗殺手，然而星敵不過，被炸傷入院，只剩腦、口，和他的penis可存活。 達求助於博士，博士說美國已發明了人造器官，但要六千萬美金，達沒錢，求助於星養父。養父一聽到這消息，便和星斷絕關係。達只有六千元，博士便以自己的研究，用最省錢的方式來改造星。為避免黑社會再追殺星，博</desc>
    <date>2025-03-07</date>
  </programme>
  <programme channel="369262" start="20250307180000 +0800" stop="20250307190000 +0800">
    <title lang="zh">少年包青天3:6</title>
    <desc>兩年前，包拯接到一封信，便匆匆離開家園，之後音訊全無。這些年裡，每當有奇案發生，公孫策便會趕赴現場，目的其實是為了尋找包拯。因公孫策諳遼語，仁宗遂委公孫策為禮部侍郎，前往宋遼邊境洽談議和。在邊境小鎮，公孫策和展昭遇到了大包——失去記憶成為妓院小雜工的包拯。失憶後的包拯傻裡傻氣，常被妓院裡的小丫鬟小蠻欺負。妓院老闆及遼國大官相繼神秘被殺，包拯找到了真凶，真凶欲殺包拯滅口，但他卻因禍得福恢復了記憶。</desc>
    <date>2025-03-07</date>
  </programme>
  <programme channel="369262" start="20250307190000 +0800" stop="20250307200000 +0800">
    <title lang="zh">倚天屠龍記:27</title>
    <desc>由楚原改編及執導，由羅烈飾金毛獅王謝遜、爾冬陞飾張無忌。劇情描述武林中人都在爭奪倚天劍、屠龍刀這兩件神器；只要這兩件神器一併，就可雄霸武林…</desc>
    <date>2025-03-07</date>
  </programme>
  <programme channel="369262" start="20250307200000 +0800" stop="20250307203000 +0800">
    <title lang="zh">實習醫師鬥格:235</title>
    <desc>改編自骨科陳建仁醫師作品的歡笑喜劇，從實習醫師的觀點來演繹白色巨塔的故事，是一部笑中帶尷尬的喜劇。</desc>
    <date>2025-03-07</date>
  </programme>
  <programme channel="369262" start="20250307203000 +0800" stop="20250307210000 +0800">
    <title lang="zh">實習醫師鬥格:236</title>
    <desc>改編自骨科陳建仁醫師作品的歡笑喜劇，從實習醫師的觀點來演繹白色巨塔的故事，是一部笑中帶尷尬的喜劇。</desc>
    <date>2025-03-07</date>
  </programme>
  <programme channel="369262" start="20250307210000 +0800" stop="20250307232000 +0800">
    <title lang="zh">夕陽天使</title>
    <desc>莫文蔚是一位外型漂亮身手矯健的年輕女探員，奉命調查一椿上海電腦商業鉅子的謀殺案，當她臥底調查此案時，和一對漂亮的姐妹花舒淇和趙薇結為好友。這對外表柔弱的姐妹花，其實是電腦和武術高手，她們有著神祕的背景，似乎還背負著一段未解決的家族血海深仇。當臥底探員莫文蔚深入調查此案時，才發現這對漂亮的姐妹花涉有重嫌。隨著她越來越接近事實的真相，她們三人的感情也出現微妙的變化，一場充滿懸疑鬥智鬥力的決鬥於焉展開。</desc>
    <date>2025-03-07</date>
  </programme>
  <programme channel="369262" start="20250307232000 +0800" stop="20250308000000 +0800">
    <title lang="zh">名偵探柯南-唐紅的戀歌</title>
    <desc>某天早上，皋月會會員矢島俊彌觀看著往年皋月杯決賽的錄影帶。這時有人手持武士刀進入矢島的房間用刀鞘將矢島給擊斃，鮮血四濺，矢島身旁的歌牌也散落一地。當天下午江戶川柯南、毛利蘭和少年偵探團陪著毛利小五郎到大阪日賣電視台與皋月會會長阿知波研介會談...</desc>
    <date>2025-03-07</date>
  </programme>
</tv>
