<?xml version='1.0' encoding='UTF-8'?>
<tv date="20260329113238 +0800" generator-info-name="epg.pw" generator-info-url="https://epg.pw/channels/410280/20260329.html" source-info-name="FREE EPG" source-info-url="https://epg.pw/api/epg.xml?channel_id=410280&amp;date=20260329&amp;timezone=QXNpYS9UYWlwZWk=">
  <channel id="410280">
    <display-name lang="Hong Kong">HBO Family</display-name>
    <icon src="https://epg.pw/media/images/epg/2025/01/28/20250128115902711757_71" />
  </channel>
  <programme channel="410280" start="20260329001500 +0800" stop="20260329003700 +0800">
    <title lang="zh">機械戰士Rex 第2季第15集 </title>
    <desc>小雷在買外賣的路上被閃靈女攔截下來，他誤以為閃靈女要去香港抓音音，於是小雷也跳進閃靈女打開的時空通道，沒想到他根本搞錯方向，閃靈女是去剋魔會的拘留所放出石怪，要石怪替梵克萊取來分子變動槍，但是石怪卻黑吃黑背叛閃靈女，最後小雷制服石怪，拿他跟閃靈女交易，救出後來被閃靈女擄走的音音。</desc>
    <date>2026-03-29</date>
  </programme>
  <programme channel="410280" start="20260329003700 +0800" stop="20260329005900 +0800">
    <title lang="zh">機械戰士Rex 第2季第16集 </title>
    <desc>何蒂博士的妹妹貝芙莉13歲就變成變魔,即使是小雷也無法治癒她,所以摩斯博士出現時,何蒂很高興,以為終於可以治好妹妹,沒想到那是個騙局,貝芙莉因此被摩斯捉走. 龍哥和小雷立刻趕去救援,才沒有造成悲劇</desc>
    <date>2026-03-29</date>
  </programme>
  <programme channel="410280" start="20260329005900 +0800" stop="20260329012100 +0800">
    <title lang="zh">機械戰士Rex 第2季第17集 </title>
    <desc>新聞節目記者黛安法拉取得進入剋魔會製作專題報導的許可,她帶著攝影機在剋魔會裡到處拍,讓大家都如臨大敵,龍哥奉命帶領她參觀,而小雷一直愛演又愛現,希望成為偶像巨星,沒想到最後出名的居然是龍哥.</desc>
    <date>2026-03-29</date>
  </programme>
  <programme channel="410280" start="20260329012100 +0800" stop="20260329014300 +0800">
    <title lang="zh">機械戰士Rex 第2季第18集 </title>
    <desc>剋魔會出外執勤時,帶回了變成石頭的叢林貓,只是他們並不知道,那石頭還會變回叢林貓. 後來就在小雷跟阿洛找朋友來開趴時,叢林貓跑來鬧場,幸好小雷及時發現他的弱點,才化解了危機</desc>
    <date>2026-03-29</date>
  </programme>
  <programme channel="410280" start="20260329014300 +0800" stop="20260329020500 +0800">
    <title lang="zh">機械戰士Rex 第2季第19集 </title>
    <desc>西薩為了協助小雷恢復過去的記憶,發明了某種機器,只是在運作中出了狀況,結果害得龍哥失去了六年時間的記憶,他完全不記得剋魔會和小雷他們的一切,還以為自己仍是個冷血無情的殺手,但是小雷對他有信心,相信他一定會再成為他心目中的英雄龍哥.</desc>
    <date>2026-03-29</date>
  </programme>
  <programme channel="410280" start="20260329020500 +0800" stop="20260329023500 +0800">
    <title lang="zh">機械戰士Rex 第2季第20集 </title>
    <desc>梵克萊利用閃靈女的超能力,企圖讓她變成史上第一位時空旅行者,小雷知道後,一直力勸閃靈女離開梵克萊,站到剋魔會這邊,因為梵克萊只是在利用她,可惜最後他還是功虧一簣.</desc>
    <date>2026-03-29</date>
  </programme>
  <programme channel="410280" start="20260329023500 +0800" stop="20260329031600 +0800">
    <title lang="zh">Top Chef Junior 第2季第12集 </title>
    <desc>首席評審柯提斯史東對選手們進行終極考驗，要求他們完美複刻他的一道招牌菜。空氣中彌漫著魔力。選手們拿起他們的魔杖，來到了魔法世界，在哈利波特的啟發下，完成一頓奇妙盛宴。每位廚師都滿心歡喜，製作野雞肉大餐，呈現給大禮堂的評審們。禮堂由新銳頂級廚師餐廳改造而成。蓋爾西蒙斯和野味專家提姆樂福擔任客串評審......《Top Chef》節目開辦以來，選手們第一次與評審坐在一起分享美食。</desc>
    <date>2026-03-29</date>
  </programme>
  <programme channel="410280" start="20260329031600 +0800" stop="20260329035700 +0800">
    <title lang="zh">Top Chef Junior 第2季第13集 </title>
    <desc>新銳頂級廚師美食爭霸賽再次打響！最後的四位廚師將在拳擊場上展開美食大戰，現場的粉絲和家人將為他們加油助威。在四輪美食大戰中，獲勝的廚師將在決賽中爭奪冠軍腰帶，而失敗的廚師還有最後一次機會留在臺上。此外，評審們結伴走上擂臺，參加幹辣椒大戰。選手們站到了評審的位置上，爆笑場面輪番襲來，現場歡快和緊張的氣氛並存。比賽再次升溫，辣椒也越來越熱。哪位廚師有實力頂住壓力，完成挑戰？大戰一觸即發。</desc>
    <date>2026-03-29</date>
  </programme>
  <programme channel="410280" start="20260329035700 +0800" stop="20260329044500 +0800">
    <title lang="zh">Top Chef Junior 第2季第14集 </title>
    <desc>最後三位廚師被鎖在了娛樂室。他們需要絞盡腦汁，揭開謎底，找到逃生的鑰匙。走出房門後，他們需要在有限的時間內做出一道精緻的貝類菜肴來打動客串評審布魯克威廉森。隨後選手們將與首席評審柯提斯史東和世界級大廚洛蕾娜加西亞一起乘船出海。選手們必須嘗試親自捕魚，慶祝首屆新銳頂級廚師釣魚節！</desc>
    <date>2026-03-29</date>
  </programme>
  <programme channel="410280" start="20260329044500 +0800" stop="20260329051500 +0800">
    <title lang="zh">荷里活現場 第1季第1160集</title>
    <desc>每個星期，「荷里活現場」為觀眾揭露三部強檔電影的幕後，為您捕捉拍攝時的鏡頭，同時訪問演員和製片。</desc>
    <date>2026-03-29</date>
  </programme>
  <programme channel="410280" start="20260329051500 +0800" stop="20260329054000 +0800">
    <title lang="zh">樂高侏羅紀公園︰非官方回憶錄</title>
    <desc>年紀漸長仍風度翩翩的混沌理論數學家伊恩馬康姆博士將娓娓道來侏羅紀公園出事的那一夜。</desc>
    <date>2026-03-29</date>
  </programme>
  <programme channel="410280" start="20260329054000 +0800" stop="20260329061500 +0800">
    <title lang="zh">童話故事集 第1季第9集 </title>
    <desc>大衛亞倫葛瑞為拉丁版的邪惡小裁縫師配音，另外還有詹姆斯厄爾和馬克寇瑞。</desc>
    <date>2026-03-29</date>
  </programme>
  <programme channel="410280" start="20260329061500 +0800" stop="20260329074500 +0800">
    <title lang="zh">早衰症男孩的快樂人生</title>
    <desc>山姆和你我一樣，都會面臨老化，但在山姆的體內格外快速，醫生在他兩歲時診斷出早老症, 父母很努力想拯救兒子，也試用第一種實驗產品，有機會讓山姆和全球28位患者延長壽命，</desc>
    <date>2026-03-29</date>
  </programme>
  <programme channel="410280" start="20260329074500 +0800" stop="20260329075700 +0800">
    <title lang="zh">松鼠洛德 第1季第24集 </title>
    <desc>安迪和洛德一天心血來潮決定交換身份，安迪當寵物，洛德當主人，同時奧斯卡為了養寵物帶父母來安迪家見習，卻發現兩人的瘋狂行徑。</desc>
    <date>2026-03-29</date>
  </programme>
  <programme channel="410280" start="20260329075700 +0800" stop="20260329080900 +0800">
    <title lang="zh">松鼠洛德 第1季第25集 </title>
    <desc>凱爾向安迪挑戰過一座危險的橋，無助的安迪和洛德於是跑去找松鼠爺爺幫忙，爺爺說了一個故事給他們聽。</desc>
    <date>2026-03-29</date>
  </programme>
  <programme channel="410280" start="20260329080900 +0800" stop="20260329082500 +0800">
    <title lang="zh">松鼠洛德 第1季第26集 -Screw</title>
    <desc>強森一家人去超級市場購物，安迪卻不小心吃了會過敏的腰果，洛德和安迪怕被處罰於是想自己解決，卻把超市弄得一團糟。</desc>
    <date>2026-03-29</date>
  </programme>
  <programme channel="410280" start="20260329082500 +0800" stop="20260329083700 +0800">
    <title lang="zh">松鼠洛德 第2季第1集 </title>
    <desc>安迪玩遊戲老是輸洛德，所以再也提不起勁玩遊戲了，所以強太太希望洛德可以讓安迪贏一次，這樣會讓安迪開心一點，但是後來洛德卻受不了安迪一直炫燿自己贏的事情。</desc>
    <date>2026-03-29</date>
  </programme>
  <programme channel="410280" start="20260329083700 +0800" stop="20260329084900 +0800">
    <title lang="zh">松鼠洛德 第2季第2集 </title>
    <desc>洛德想要加入強森俱樂部但是遭到拒絕，只好轉去參加淑女俱樂部，他在淑女俱樂部大受歡迎，讓強太太整天都在講洛德，強先生只好讓洛德加入…</desc>
    <date>2026-03-29</date>
  </programme>
  <programme channel="410280" start="20260329084900 +0800" stop="20260329090100 +0800">
    <title lang="zh">松鼠洛德 第2季第3集 </title>
    <desc>洛德的表哥艾迪有一天突然造訪洛德及安迪，剛開始洛德並不是很開心見到表哥艾迪，然而在艾迪的柔情攻勢下，洛德漸漸心軟並開始跟他一起遊玩，後來洛德發現這原來是艾迪表哥為了逃離噁心老鼠的追殺，所設下的一個騙局，為此安迪想出了一個報復的方式讓表哥艾迪嚐盡了苦頭。</desc>
    <date>2026-03-29</date>
  </programme>
  <programme channel="410280" start="20260329090100 +0800" stop="20260329091300 +0800">
    <title lang="zh">松鼠洛德 第2季第4集 </title>
    <desc>洛德想要約達琳一起出去玩，達琳答應了並約了安迪和馬莎，洛德將達琳最喜歡的黃色水仙花記成她最討厭的碰碰車，因而整天約會都被搞砸了，但馬莎和安迪因為一起完成照相的企劃而變成要好的朋友，他們因此協議下一次一同再出去玩。</desc>
    <date>2026-03-29</date>
  </programme>
  <programme channel="410280" start="20260329091300 +0800" stop="20260329092500 +0800">
    <title lang="zh">松鼠洛德 第2季第5集 </title>
    <desc>安迪和洛德為佛萊巴頓太太做家事做為處罰的時候，喝到了美味的檸檬汁，而想一直為她做家事來交換檸檬汁，凱爾和鹽巴麥克也嚐到了檸檬汁的美味，一直想要讓佛萊巴頓太太處罰他們來交換好喝的檸檬汁，他們能如願嗎？</desc>
    <date>2026-03-29</date>
  </programme>
  <programme channel="410280" start="20260329092500 +0800" stop="20260329093700 +0800">
    <title lang="zh">松鼠洛德 第2季第6集 </title>
    <desc>強生夫婦為慶祝結婚週年一起度假去了，留下安迪和洛德。因為說好的朋友家臨時有事，所以得拜託凱爾的爸媽代為照顧。正好讓安迪和洛德落入凱爾和鹽巴麥克的手中。他們要如何躲避凱爾和鹽巴麥克的虐待呢？</desc>
    <date>2026-03-29</date>
  </programme>
  <programme channel="410280" start="20260329093700 +0800" stop="20260329094900 +0800">
    <title lang="zh">松鼠洛德 第2季第7集 </title>
    <desc>失而復得-安迪和洛德為了玩遊戲偷拿爸爸的保齡球獎盃，結果卻落入隔壁的瘋狗手中。牠們要怎麼把爸爸心愛的獎盃拿回來呢？</desc>
    <date>2026-03-29</date>
  </programme>
  <programme channel="410280" start="20260329094900 +0800" stop="20260329100100 +0800">
    <title lang="zh">松鼠洛德 第2季第8集 </title>
    <desc>因為洛德太愛亂花錢，安迪很擔心未來會很窮，於是在爸爸的訓練下開始了存錢大計。洛德卻不斷地亂花錢，讓安迪抓狂失控…</desc>
    <date>2026-03-29</date>
  </programme>
  <programme channel="410280" start="20260329100100 +0800" stop="20260329101300 +0800">
    <title lang="zh">松鼠洛德 第2季第9集 </title>
    <desc>安迪跟凱爾要進行蓋樹屋比賽，看誰蓋的比較好。</desc>
    <date>2026-03-29</date>
  </programme>
  <programme channel="410280" start="20260329101300 +0800" stop="20260329102500 +0800">
    <title lang="zh">松鼠洛德 第2季第10集 </title>
    <desc>凱爾的鸚鵡被買走了，所以要安迪的羅尼扮成鸚鵡來陪他，但是安迪為了要甩掉凱爾，決定要大家一起去把麥克偷回來…</desc>
    <date>2026-03-29</date>
  </programme>
  <programme channel="410280" start="20260329102500 +0800" stop="20260329103700 +0800">
    <title lang="zh">松鼠洛德 第2季第11集 </title>
    <desc>凱爾和鹽巴麥克想捉弄安迪，但是安迪和鹽巴麥克卻發現了彼此共同的嗜好，到底他們是否能成為好朋友呢?</desc>
    <date>2026-03-29</date>
  </programme>
  <programme channel="410280" start="20260329103700 +0800" stop="20260329104900 +0800">
    <title lang="zh">松鼠洛德 第2季第12集 </title>
    <desc>年邁的導護員(愛摩)要退休了，安迪想要成為新的導護員就必須想辦法打敗強勁的對手(神氣傑克).</desc>
    <date>2026-03-29</date>
  </programme>
  <programme channel="410280" start="20260329104900 +0800" stop="20260329110100 +0800">
    <title lang="zh">松鼠洛德 第2季第13集 </title>
    <desc>強森先生要去參加種花比賽，但是安迪和洛德把花都搞爛了。</desc>
    <date>2026-03-29</date>
  </programme>
  <programme channel="410280" start="20260329110100 +0800" stop="20260329111300 +0800">
    <title lang="zh">松鼠洛德 第2季第14集 </title>
    <desc>安迪突發奇想想要辦報紙給爸爸看，沒想到卻演變成三人戰爭。</desc>
    <date>2026-03-29</date>
  </programme>
  <programme channel="410280" start="20260329111300 +0800" stop="20260329112500 +0800">
    <title lang="zh">松鼠洛德 第2季第15集 </title>
    <desc>強森先生跟家人去度假，以為洛德沒跟來，但是他躲在車底一路跟著去。</desc>
    <date>2026-03-29</date>
  </programme>
  <programme channel="410280" start="20260329112500 +0800" stop="20260329113700 +0800">
    <title lang="zh">松鼠洛德 第2季第16集 </title>
    <desc>巴區是隻野松鼠，侵占李奧的家，然後又闖進安迪的家，洛德跟安迪為了要把他趕走，只好去找巴區的媽媽…</desc>
    <date>2026-03-29</date>
  </programme>
  <programme channel="410280" start="20260329113700 +0800" stop="20260329114900 +0800">
    <title lang="zh">松鼠洛德 第2季第17集 -Ice Cream Anti</title>
    <desc>瑪莎在安迪家前院蓋東西，讓安迪很想知道她在蓋什麼，問她又不說，所以他去找大衛聽聽他有什麼建議。</desc>
    <date>2026-03-29</date>
  </programme>
  <programme channel="410280" start="20260329114900 +0800" stop="20260329120100 +0800">
    <title lang="zh">松鼠洛德 第2季第18集 </title>
    <desc>隔壁的瘋狗一直在叫，讓安迪跟洛德受不了一起去抱怨。</desc>
    <date>2026-03-29</date>
  </programme>
  <programme channel="410280" start="20260329120100 +0800" stop="20260329121300 +0800">
    <title lang="zh">松鼠洛德 第2季第19集 </title>
    <desc>洛德做什麼壞事都不會被罵，因為大家覺得他只是一隻松鼠，所以他就以這個強項開業，代替別人挨罵，但是他後來覺悟了…</desc>
    <date>2026-03-29</date>
  </programme>
  <programme channel="410280" start="20260329121300 +0800" stop="20260329122500 +0800">
    <title lang="zh">松鼠洛德 第2季第20集 </title>
    <desc>帕哥是一隻電視明星狗，安迪跟洛德都愛死他了，有一天帕哥去他們家附近拍攝節目，但是後來出現在安迪家，安迪跟洛德還帶他去商場逛街，讓大家都羨慕死了…</desc>
    <date>2026-03-29</date>
  </programme>
  <programme channel="410280" start="20260329122500 +0800" stop="20260329123700 +0800">
    <title lang="zh">松鼠洛德 第2季第21集 </title>
    <desc>安迪和洛德產生了小摩擦，達琳想要讓兩人言歸於好，於是使出許多方法。</desc>
    <date>2026-03-29</date>
  </programme>
  <programme channel="410280" start="20260329123700 +0800" stop="20260329130500 +0800">
    <title lang="zh">松鼠洛德 第2季第22集 </title>
    <desc>家裡出現了一個會說話的魚標本，一直指引洛德去幫助大家做事情。</desc>
    <date>2026-03-29</date>
  </programme>
  <programme channel="410280" start="20260329130500 +0800" stop="20260329144500 +0800">
    <title lang="zh">狗店風雲</title>
    <desc>16歲的安蒂和弟弟布魯斯來到寄養家庭，發現新家庭的爸媽嚴格規定不准養寵物，於是他們必須儘快為自己的寵物狗佛萊迪找到新家。</desc>
    <date>2026-03-29</date>
  </programme>
  <programme channel="410280" start="20260329144500 +0800" stop="20260329172000 +0800">
    <title lang="zh">哈利波特 混血王子的背叛</title>
    <desc>佛地魔率領食死人向麻瓜和魔法世界伸出魔爪，哈利懷疑霍格華茲正面臨全新危險。</desc>
    <date>2026-03-29</date>
  </programme>
  <programme channel="410280" start="20260329172000 +0800" stop="20260329180200 +0800">
    <title lang="zh">Top Chef 第17季第13集 </title>
    <desc>在這場全明星賽的倒數第二集中，眾人前往帕爾馬繼續烹飪夢想之旅。這裡是帕爾馬乾酪和帕馬火腿之鄉。廚師們參觀完製作這些特色產品的歷史悠久的工廠後，必須使用這些原料完成兩道菜的製作並接受16位米芝蓮星級廚師的點評。麵點大師埃文馮克與湯姆、帕德瑪、蓋爾和一眾著名義大利廚師一起擔任評審。一名選手被淘汰，前三名進入決賽。</desc>
    <date>2026-03-29</date>
  </programme>
  <programme channel="410280" start="20260329180200 +0800" stop="20260329190000 +0800">
    <title lang="zh">Top Chef 第17季第14集 </title>
    <desc>在這場史詩級的義大利美食比賽中，最後三位選手將獻上迄今為止做過的最重要的一道美味，斬獲冠軍頭銜和獎品。三人不僅需要打動評審——湯姆、帕德瑪、蓋爾和尼魯莫泰咪德，還需要令美食名人毛羅柯拉格雷科、克萊爾史密斯、馬庫斯薩繆爾森、黃慧嫻、托尼曼圖亞諾、第八代義大利屠夫達裡奧塞奇尼和《美食與美酒》雜誌主編亨特路易士刮目相看。三人陷入苦戰，其中一人將獲得頂級廚師的稱號。</desc>
    <date>2026-03-29</date>
  </programme>
  <programme channel="410280" start="20260329190000 +0800" stop="20260329204000 +0800">
    <title lang="zh">談談情‧錫錫狗</title>
    <desc>愛狗卻沒養狗的莎拉，到了和傑克見面的那天，她不得不向哥哥借隻狗來充數，卻沒想到，傑克的狗也非他所有，真愛到底會不會上門呢？</desc>
    <date>2026-03-29</date>
  </programme>
  <programme channel="410280" start="20260329204000 +0800" stop="20260329221500 +0800">
    <title lang="zh">壞蛋獎門人4</title>
    <desc>最惹人愛的犯罪首腦、以及他那群語無倫次卻可愛至極的黃色小小兵第四度現身，充滿了驚奇冒險與家庭惡趣味。</desc>
    <date>2026-03-29</date>
  </programme>
  <programme channel="410280" start="20260329221500 +0800" stop="20260329225700 +0800">
    <title lang="zh">露比與魔法井 第2季第6集 </title>
    <desc>魯比看見了新願望的提示，卻無從得知願望是什麼。</desc>
    <date>2026-03-29</date>
  </programme>
  <programme channel="410280" start="20260329225700 +0800" stop="20260329233800 +0800">
    <title lang="zh">露比與魔法井 第2季第7集 </title>
    <desc>魯比和朋友們努力實現一位非常嚇人又神秘的人所許的願望。</desc>
    <date>2026-03-29</date>
  </programme>
  <programme channel="410280" start="20260329233800 +0800" stop="20260330000000 +0800">
    <title lang="zh">露比與魔法井 第2季第8集 </title>
    <desc>魯比和朋友們展開了一場刺激且意外的冒險。</desc>
    <date>2026-03-29</date>
  </programme>
  <programme channel="410280" start="20260330002000 +0800" stop="20260330010200 +0800">
    <title lang="zh">露比與魔法井 第2季第9集 </title>
    <desc>魯比得解決一場長久的家族對立。</desc>
    <date>2026-03-30</date>
  </programme>
  <programme channel="410280" start="20260330010200 +0800" stop="20260330015500 +0800">
    <title lang="zh">露比與魔法井 第2季第10集 </title>
    <desc>魯比收到了有史以來最困難的願望，而且，這可能會是最後一個願望。</desc>
    <date>2026-03-30</date>
  </programme>
  <programme channel="410280" start="20260330015500 +0800" stop="20260330024000 +0800">
    <title lang="zh">Top Chef Junior 第2季第15集 </title>
    <desc>第二季總決賽開始了。選手們和“頂級廚師”頭銜之間僅有一步之遙：彼此。最後兩位選手必須全力以赴，做出生平中最重要的一餐。《Top Chef Junior》第一季進入總決賽的選手蕾哈娜和歐文，以及烹飪界的傳奇人物艾默利拉加西都將在這一重要時刻蒞臨現場。最後的兩位廚師將使出絕技，展示從年輕廚師到資深廚師的蛻變。為了幫助他們完成這項艱巨的任務，一些熟悉的面孔回到了節目現場......這些老熟人會不會伸出援手，還是說現場廚師人滿為患？最終僅會有一名決賽選手獲得“新銳頂級廚師”的稱號。</desc>
    <date>2026-03-30</date>
  </programme>
  <programme channel="410280" start="20260330024000 +0800" stop="20260330033000 +0800">
    <title lang="zh">撕裂記憶體 第1季第1集</title>
    <desc>喬治發現自己正在重新經歷同樣的幾週時間，獲得一個會改變人生的重大邀請。</desc>
    <date>2026-03-30</date>
  </programme>
  <programme channel="410280" start="20260330033000 +0800" stop="20260330055000 +0800">
    <title lang="zh">狂舞紐約</title>
    <desc>著名舞台劇《漢密爾頓》（Hamilton）的創造者，聯手【瘋狂亞洲富豪】的導演，邀您參與這場電影饗宴——【紐約高地】。在這裡，街區充滿美妙旋律，而小小夢想會變得偉大。</desc>
    <date>2026-03-30</date>
  </programme>
  <programme channel="410280" start="20260330055000 +0800" stop="20260330074000 +0800">
    <title lang="zh">小飛俠：魔幻始源</title>
    <desc>孤兒彼得被帶往神奇的夢幻島，在這裡他找到樂趣也遭受危險，最後發現自己真正的命運-成為世人所熟知的英雄彼得潘。</desc>
    <date>2026-03-30</date>
  </programme>
  <programme channel="410280" start="20260330074000 +0800" stop="20260330075100 +0800">
    <title lang="zh">瘋狂夏令營 第1季第14集 </title>
    <desc>豆子童軍因為沒有馬匹而鬱鬱寡歡，但拉茲洛找來了愛吐口水的駱馬後情況改變，他們發現自己就算是異類也沒關係。</desc>
    <date>2026-03-30</date>
  </programme>
  <programme channel="410280" start="20260330075100 +0800" stop="20260330080300 +0800">
    <title lang="zh">瘋狂夏令營 第1季第15集 </title>
    <desc>軟糖小隊發現新養的寵物蛇在小屋不見了，佩西出手拯救夏令營，以免凶猛的小過山刀一個個吃掉大家。</desc>
    <date>2026-03-30</date>
  </programme>
  <programme channel="410280" start="20260330080300 +0800" stop="20260330081400 +0800">
    <title lang="zh">瘋狂夏令營 第1季第16集 </title>
    <desc>史林克對軟糖小隊很失望，因為他們花掉了所有拿來造車的錢，但他們靠著獨創車體，贏得賽車比賽以彌補過錯！</desc>
    <date>2026-03-30</date>
  </programme>
  <programme channel="410280" start="20260330081400 +0800" stop="20260330082500 +0800">
    <title lang="zh">瘋狂夏令營 第1季第17集 </title>
    <desc>洛基的維持器掉了，夏令營的整趟搭船行程中，他一直神經兮兮地想找到維持器，直到拉茲洛點醒了他。</desc>
    <date>2026-03-30</date>
  </programme>
  <programme channel="410280" start="20260330082500 +0800" stop="20260330083700 +0800">
    <title lang="zh">瘋狂夏令營 第1季第18集 </title>
    <desc>拉茲洛找到找到一頂假髮，假扮成預測未來的智者，但夏令營的同伴發現預言成真後都感到毛骨悚然。</desc>
    <date>2026-03-30</date>
  </programme>
  <programme channel="410280" start="20260330083700 +0800" stop="20260330090000 +0800">
    <title lang="zh">瘋狂夏令營 第1季第19集 </title>
    <desc>蘭巴斯不准史林克晚上休假，拉茲洛幫史林克挺身反抗上司。</desc>
    <date>2026-03-30</date>
  </programme>
  <programme channel="410280" start="20260330090000 +0800" stop="20260330091200 +0800">
    <title lang="zh">松鼠洛德 第2季第18集 </title>
    <desc>隔壁的瘋狗一直在叫，讓安迪跟洛德受不了一起去抱怨。</desc>
    <date>2026-03-30</date>
  </programme>
  <programme channel="410280" start="20260330091200 +0800" stop="20260330092400 +0800">
    <title lang="zh">松鼠洛德 第2季第19集 </title>
    <desc>洛德做什麼壞事都不會被罵，因為大家覺得他只是一隻松鼠，所以他就以這個強項開業，代替別人挨罵，但是他後來覺悟了…</desc>
    <date>2026-03-30</date>
  </programme>
  <programme channel="410280" start="20260330092400 +0800" stop="20260330093600 +0800">
    <title lang="zh">松鼠洛德 第2季第20集 </title>
    <desc>帕哥是一隻電視明星狗，安迪跟洛德都愛死他了，有一天帕哥去他們家附近拍攝節目，但是後來出現在安迪家，安迪跟洛德還帶他去商場逛街，讓大家都羨慕死了…</desc>
    <date>2026-03-30</date>
  </programme>
  <programme channel="410280" start="20260330093600 +0800" stop="20260330094800 +0800">
    <title lang="zh">松鼠洛德 第2季第21集 </title>
    <desc>安迪和洛德產生了小摩擦，達琳想要讓兩人言歸於好，於是使出許多方法。</desc>
    <date>2026-03-30</date>
  </programme>
  <programme channel="410280" start="20260330094800 +0800" stop="20260330100500 +0800">
    <title lang="zh">松鼠洛德 第2季第22集 </title>
    <desc>家裡出現了一個會說話的魚標本，一直指引洛德去幫助大家做事情。</desc>
    <date>2026-03-30</date>
  </programme>
  <programme channel="410280" start="20260330100500 +0800" stop="20260330105000 +0800">
    <title lang="zh">露比與魔法井 第2季第10集 </title>
    <desc>魯比收到了有史以來最困難的願望，而且，這可能會是最後一個願望。</desc>
    <date>2026-03-30</date>
  </programme>
  <programme channel="410280" start="20260330105000 +0800" stop="20260330111500 +0800">
    <title lang="zh">機械戰士Rex 第2季第19集 </title>
    <desc>西薩為了協助小雷恢復過去的記憶,發明了某種機器,只是在運作中出了狀況,結果害得龍哥失去了六年時間的記憶,他完全不記得剋魔會和小雷他們的一切,還以為自己仍是個冷血無情的殺手,但是小雷對他有信心,相信他一定會再成為他心目中的英雄龍哥.</desc>
    <date>2026-03-30</date>
  </programme>
  <programme channel="410280" start="20260330111500 +0800" stop="20260330114000 +0800">
    <title lang="zh">機械戰士Rex 第2季第20集 </title>
    <desc>梵克萊利用閃靈女的超能力,企圖讓她變成史上第一位時空旅行者,小雷知道後,一直力勸閃靈女離開梵克萊,站到剋魔會這邊,因為梵克萊只是在利用她,可惜最後他還是功虧一簣.</desc>
    <date>2026-03-30</date>
  </programme>
  <programme channel="410280" start="20260330114000 +0800" stop="20260330132000 +0800">
    <title lang="zh">談談情‧錫錫狗</title>
    <desc>愛狗卻沒養狗的莎拉，到了和傑克見面的那天，她不得不向哥哥借隻狗來充數，卻沒想到，傑克的狗也非他所有，真愛到底會不會上門呢？</desc>
    <date>2026-03-30</date>
  </programme>
  <programme channel="410280" start="20260330132000 +0800" stop="20260330145500 +0800">
    <title lang="zh">壞蛋獎門人4</title>
    <desc>最惹人愛的犯罪首腦、以及他那群語無倫次卻可愛至極的黃色小小兵第四度現身，充滿了驚奇冒險與家庭惡趣味。</desc>
    <date>2026-03-30</date>
  </programme>
  <programme channel="410280" start="20260330145500 +0800" stop="20260330150700 +0800">
    <title lang="zh">瘋狂夏令營 第1季第20集 </title>
    <desc>軟糖小隊發現自己很擅長做熱狗，夏令營的「名聲」讓他們沖昏了頭！</desc>
    <date>2026-03-30</date>
  </programme>
  <programme channel="410280" start="20260330150700 +0800" stop="20260330151800 +0800">
    <title lang="zh">瘋狂夏令營 第1季第21集 </title>
    <desc>蘭巴斯在鎮上的餐廳吃「霸王餐」，如果他沒留下軟糖小隊，他就不會被抓到了！</desc>
    <date>2026-03-30</date>
  </programme>
  <programme channel="410280" start="20260330151800 +0800" stop="20260330152900 +0800">
    <title lang="zh">瘋狂夏令營 第1季第22集 </title>
    <desc>拉茲洛希望大家停止洗澡，一起變臭，但三森吹毛求疵的方式阻擋了他的「骯髒」計畫。</desc>
    <date>2026-03-30</date>
  </programme>
  <programme channel="410280" start="20260330152900 +0800" stop="20260330154100 +0800">
    <title lang="zh">瘋狂夏令營 第1季第23集 </title>
    <desc>史克林臥底變裝以找出是誰一直捉弄大麋鹿。</desc>
    <date>2026-03-30</date>
  </programme>
  <programme channel="410280" start="20260330154100 +0800" stop="20260330155200 +0800">
    <title lang="zh">瘋狂夏令營 第1季第24集 </title>
    <desc>艾德華年紀太小不能看夏令營的電影，為了證明自己夠成熟足以消化電影內容，他還因此有些失控—他當然還太小不能看！</desc>
    <date>2026-03-30</date>
  </programme>
  <programme channel="410280" start="20260330155200 +0800" stop="20260330161500 +0800">
    <title lang="zh">瘋狂夏令營 第1季第25集 </title>
    <desc>蘭巴斯發現洛基有塊珍貴的印度輪狀起司，蘭巴斯想方設法要親自嚐嚐。</desc>
    <date>2026-03-30</date>
  </programme>
  <programme channel="410280" start="20260330161500 +0800" stop="20260330162700 +0800">
    <title lang="zh">松鼠洛德 第2季第23集 </title>
    <desc>刮風下雨讓李奧想要走進家庭當寵物，洛德四處幫牠徵求主人，結果李奧來到奧斯卡的家當寵物。</desc>
    <date>2026-03-30</date>
  </programme>
  <programme channel="410280" start="20260330162700 +0800" stop="20260330163900 +0800">
    <title lang="zh">松鼠洛德 第2季第24集 </title>
    <desc>亞奇又回來了，牠懷著滿滿報復的心，這次聯合了喜歡惡作劇整洛德的鹽巴麥克要狠狠地回敬洛德一記。</desc>
    <date>2026-03-30</date>
  </programme>
  <programme channel="410280" start="20260330163900 +0800" stop="20260330165100 +0800">
    <title lang="zh">松鼠洛德 第2季第25集 </title>
    <desc>洛德的表弟愛迪來拜訪，因為他會飛所以非常受歡迎，這讓洛德非常受不了，所以去找松鼠爺爺幫忙，然後爺爺跟他說了一個西部故事，希望他能明白其中的道理。</desc>
    <date>2026-03-30</date>
  </programme>
  <programme channel="410280" start="20260330165100 +0800" stop="20260330171000 +0800">
    <title lang="zh">松鼠洛德 第2季第26集 </title>
    <desc>安迪他們在玩想像的遊戲，但是真的滅鼠人出現了，而且想要殺掉李奧，他們到底應該如何對付他呢…</desc>
    <date>2026-03-30</date>
  </programme>
  <programme channel="410280" start="20260330171000 +0800" stop="20260330172300 +0800">
    <title lang="zh">松鼠洛德 第1季第1集 </title>
    <desc>三明治的秘密-安迪和洛德想要買好東西而開始祖傳三明治的生意，但洛德一直認為是牠的帽子讓三明治大賣，安迪因為這樣很生氣。他們到底能不能湊到錢來買好東西呢？</desc>
    <date>2026-03-30</date>
  </programme>
  <programme channel="410280" start="20260330172300 +0800" stop="20260330174000 +0800">
    <title lang="zh">松鼠洛德 第1季第2集 </title>
    <desc>洛德是隻博學多聞又風趣的松鼠，總是有用不完的新點子。10歲的安迪是洛德最要好的朋友，而洛德也同時是安迪的寵物。這對「搗蛋耍寶」組合，在安迪家的後院和鄰居間展開各式各樣的冒險行動，Cartoon Network將有趣的動物帶入家庭生活中，千萬不可錯過！</desc>
    <date>2026-03-30</date>
  </programme>
  <programme channel="410280" start="20260330174000 +0800" stop="20260330180500 +0800">
    <title lang="zh">機械戰士Rex 第1季第1集 </title>
    <desc>地球在五年前發生了驚天巨變，所有生物都遭到幻晶入侵，受害者被稱為Evos(變魔) ，有些人會變成怪物，到處作亂，但是得天獨厚的Rex小雷，卻能隨心所欲的掌控體內的幻晶，將身體變成威力強大的機械，他還擁有治癒變魔的超能力，這使得他成為救世主。</desc>
    <date>2026-03-30</date>
  </programme>
  <programme channel="410280" start="20260330180500 +0800" stop="20260330183000 +0800">
    <title lang="zh">機械戰士Rex 第1季第2集 </title>
    <desc>小雷和龍哥奉命處理變魔亂象，他們必須治好科學家彼得變身的變魔，但彼得不願意接受治療，他好像有苦衷，但是白爵士下令殲滅所有受他控制的變魔，小雷認為應該要查明真相，所以他決定抗命，協助彼得。</desc>
    <date>2026-03-30</date>
  </programme>
  <programme channel="410280" start="20260330183000 +0800" stop="20260330190000 +0800">
    <title lang="zh">機械戰士Rex 第1季第3集 </title>
    <desc>成天悶在剋魔會裡沒事做的小雷，決定跟哈哈和阿洛一起去熱帶小島放大假，沒想到他在島上，認識了同是Evo的音音，兩人還聯手對付了大海怪。小雷和音音對彼此都有好感，只是音音一心只想加入梵獸群，小雷只好跟她黯然道別。</desc>
    <date>2026-03-30</date>
  </programme>
  <programme channel="410280" start="20260330190000 +0800" stop="20260330203500 +0800">
    <title lang="zh">完美巨聲幫3</title>
    <desc>在倍受影迷喜愛的《歌喉讚》系列電影最終章中，已從大學畢業並明白社會現實的美麗女聲們再度聚首，最後一次共同創造美妙的音樂。</desc>
    <date>2026-03-30</date>
  </programme>
  <programme channel="410280" start="20260330203500 +0800" stop="20260330222000 +0800">
    <title lang="zh">魔獸戰車</title>
    <desc>高中生崔普發現一個以石油為生的生物曲奇，並為這個新朋友展開一段尋親之旅。</desc>
    <date>2026-03-30</date>
  </programme>
  <programme channel="410280" start="20260330222000 +0800" stop="20260331000000 +0800">
    <title lang="zh">Minecraft：我的世界大電影</title>
    <desc>本片是首部由史上最暢銷遊戲「麥塊」改編的大銀幕真人電影。</desc>
    <date>2026-03-30</date>
  </programme>
  <programme channel="410280" start="20260331000000 +0800" stop="20260401000000 +0800">
    <title lang="zh">撕裂記憶體 第1季第1集</title>
    <desc>喬治發現自己正在重新經歷同樣的幾週時間，獲得一個會改變人生的重大邀請。</desc>
    <date>2026-03-31</date>
  </programme>
</tv>
