<?xml version='1.0' encoding='UTF-8'?>
<tv date="20250216095914 +0800" generator-info-name="epg.pw" generator-info-url="https://epg.pw/channels/368790/20250216.html" source-info-name="FREE EPG" source-info-url="https://epg.pw/api/epg.xml?channel_id=368790&amp;date=20250216&amp;timezone=QXNpYS9UYWlwZWk=">
  <channel id="368790">
    <display-name lang="Taiwan">龍華戲劇HD</display-name>
    <icon src="https://epg.pw/media/images/epg/2024/06/09/20240609115907037893_16.png" />
  </channel>
  <programme channel="368790" start="20250216000000 +0800" stop="20250216020000 +0800">
    <title lang="zh">軍師聯盟 Ⅱ(13-14)(普)</title>
    <desc />
    <date>2025-02-16</date>
  </programme>
  <programme channel="368790" start="20250216020000 +0800" stop="20250216050000 +0800">
    <title lang="zh">開創盛世(15-17)(普)</title>
    <desc />
    <date>2025-02-16</date>
  </programme>
  <programme channel="368790" start="20250216050000 +0800" stop="20250216070000 +0800">
    <title lang="zh">台灣60赫茲(首)(29-30)(普)</title>
    <desc />
    <date>2025-02-16</date>
  </programme>
  <programme channel="368790" start="20250216070000 +0800" stop="20250216100000 +0800">
    <title lang="zh">開創盛世(18-20)(普)</title>
    <desc />
    <date>2025-02-16</date>
  </programme>
  <programme channel="368790" start="20250216100000 +0800" stop="20250216110000 +0800">
    <title lang="zh">今天不算命(普)</title>
    <desc />
    <date>2025-02-16</date>
  </programme>
  <programme channel="368790" start="20250216110000 +0800" stop="20250216150000 +0800">
    <title lang="zh">善德女王(41-44)(普)</title>
    <desc />
    <date>2025-02-16</date>
  </programme>
  <programme channel="368790" start="20250216150000 +0800" stop="20250216160000 +0800">
    <title lang="zh">今天不算命(普)</title>
    <desc />
    <date>2025-02-16</date>
  </programme>
  <programme channel="368790" start="20250216160000 +0800" stop="20250216200000 +0800">
    <title lang="zh">軍師聯盟 Ⅱ(15-18)(普)</title>
    <desc />
    <date>2025-02-16</date>
  </programme>
  <programme channel="368790" start="20250216200000 +0800" stop="20250216220000 +0800">
    <title lang="zh">台灣60赫茲(首)(31-32)(普)</title>
    <desc />
    <date>2025-02-16</date>
  </programme>
  <programme channel="368790" start="20250216220000 +0800" stop="20250217000000 +0800">
    <title lang="zh">軍師聯盟 Ⅱ(15-16)(普)</title>
    <desc />
    <date>2025-02-16</date>
  </programme>
  <programme channel="368790" start="20250217000000 +0800" stop="20250217020000 +0800">
    <title lang="zh">快意恩仇武當劍(17-18)(普)</title>
    <desc />
    <date>2025-02-17</date>
  </programme>
  <programme channel="368790" start="20250217020000 +0800" stop="20250217040000 +0800">
    <title lang="zh">世上最漂亮的女兒(首)(51-52)(普)</title>
    <desc />
    <date>2025-02-17</date>
  </programme>
  <programme channel="368790" start="20250217040000 +0800" stop="20250217060000 +0800">
    <title lang="zh">銀行家(首)(10-11)(普)</title>
    <desc />
    <date>2025-02-17</date>
  </programme>
  <programme channel="368790" start="20250217060000 +0800" stop="20250217080000 +0800">
    <title lang="zh">九流霸主(29-30)(普)</title>
    <desc />
    <date>2025-02-17</date>
  </programme>
  <programme channel="368790" start="20250217080000 +0800" stop="20250217100000 +0800">
    <title lang="zh">仁心仁術：皇甫神醫(17-18)(普)</title>
    <desc />
    <date>2025-02-17</date>
  </programme>
  <programme channel="368790" start="20250217100000 +0800" stop="20250217110000 +0800">
    <title lang="zh">今天不算命(普)</title>
    <desc />
    <date>2025-02-17</date>
  </programme>
  <programme channel="368790" start="20250217110000 +0800" stop="20250217130000 +0800">
    <title lang="zh">大秦賦(27-28)(普)</title>
    <desc />
    <date>2025-02-17</date>
  </programme>
  <programme channel="368790" start="20250217130000 +0800" stop="20250217140000 +0800">
    <title lang="zh">包青天(貍貓換太子)(4)(普)</title>
    <desc />
    <date>2025-02-17</date>
  </programme>
  <programme channel="368790" start="20250217140000 +0800" stop="20250217160000 +0800">
    <title lang="zh">快意恩仇武當劍(17-18)(普)</title>
    <desc />
    <date>2025-02-17</date>
  </programme>
  <programme channel="368790" start="20250217160000 +0800" stop="20250217180000 +0800">
    <title lang="zh">大秦賦(29-30)(普)</title>
    <desc />
    <date>2025-02-17</date>
  </programme>
  <programme channel="368790" start="20250217180000 +0800" stop="20250217200000 +0800">
    <title lang="zh">九流霸主(首)(31-32)(普)</title>
    <desc />
    <date>2025-02-17</date>
  </programme>
  <programme channel="368790" start="20250217200000 +0800" stop="20250217220000 +0800">
    <title lang="zh">快意恩仇武當劍(新)(19-20)(普)</title>
    <desc />
    <date>2025-02-17</date>
  </programme>
  <programme channel="368790" start="20250217220000 +0800" stop="20250218000000 +0800">
    <title lang="zh">仁心仁術：皇甫神醫(新)(19-20)(普)</title>
    <desc />
    <date>2025-02-17</date>
  </programme>
  <programme channel="368790" start="20250218000000 +0800" stop="20250219000000 +0800">
    <title lang="zh">快意恩仇武當劍(19-20)(普)</title>
    <desc />
    <date>2025-02-18</date>
  </programme>
</tv>
